bokchoi/__init__.py
bokchoi/bokchoi.py
bokchoi/cli.py
bokchoi/config.py
bokchoi/ssh.py
bokchoi/utils.py
bokchoi/aws/__init__.py
bokchoi/aws/cloudwatch_logger.py
bokchoi/aws/common.py
bokchoi/aws/ec2-startup-script.sh
bokchoi/aws/ec2.py
bokchoi/aws/emr.py
bokchoi/gcp/__init__.py
bokchoi/gcp/gcp-startup-script.sh
bokchoi/gcp/gcp.py
bokchoi-0.4.4.dist-info/METADATA
bokchoi-0.4.4.dist-info/RECORD
bokchoi-0.4.4.dist-info/WHEEL
bokchoi-0.4.4.dist-info/entry_points.txt
bokchoi-0.4.4.dist-info/top_level.txt
